{
    "starting_win_prob": 0.5039486289,
    "game_datapoints": [
        {
            "start_utc": 1694289613,
            "end_utc": 1694290483,
            "home_vals": {
                "tone_pos": 0.5746884916457022,
                "tone_neg": 0.6853933155937256,
                "emotion": 0.5749035393451479,
                "emo_pos": 0.2927537447110402,
                "emo_neg": 0.6774483094079393,
                "emo_anx": 0.14530531038336697,
                "emo_anger": 0.0,
                "emo_sad": 0.6425371869773746,
                "i": 0.6663778861264456,
                "we": 0.10957276437464485,
                "you": 0.9397071862632723,
                "shehe": 0.0,
                "they": 0.10423484470613996,
                "conflict": 0.0,
                "want": 0.0,
                "comment_count": 0.0783132530120482
            },
            "away_vals": {
                "tone_pos": 0.9133664011635483,
                "tone_neg": 0.3029225288898547,
                "emotion": 0.90432552344486,
                "emo_pos": 0.9066088966444843,
                "emo_neg": 0.361674075854059,
                "emo_anx": 0.0,
                "emo_anger": 0.39157719643127176,
                "emo_sad": 0.0,
                "i": 0.5522088353413656,
                "we": 0.3190732034922768,
                "you": 0.1971043013775653,
                "shehe": 0.0,
                "they": 0.07233456090011521,
                "conflict": 0.09275561668959191,
                "want": 0.3451819032952865,
                "comment_count": 0.21084337349397592
            },
            "neut_vals": {
                "tone_pos": 0.4915843931317206,
                "tone_neg": 0.666855070982328,
                "emotion": 0.716166695674035,
                "emo_pos": 0.41851388755303354,
                "emo_neg": 0.7590069463913028,
                "emo_anx": 0.36838580040187546,
                "emo_anger": 0.20718144701208369,
                "emo_sad": 0.9568919730781621,
                "i": 0.8499849199168212,
                "we": 0.5687099334513708,
                "you": 0.0,
                "shehe": 0.2463955486457737,
                "they": 0.18812703981136683,
                "conflict": 0.0,
                "want": 0.32381907388174613,
                "comment_count": 0.3313253012048193
            },
            "wp_delta": -0.2063037157
        },
        {
            "start_utc": 1694290514,
            "end_utc": 1694291742,
            "home_vals": {
                "tone_pos": 0.8570730442299379,
                "tone_neg": 0.2572551094649117,
                "emotion": 0.7019714954265054,
                "emo_pos": 0.6596304489542925,
                "emo_neg": 0.3013727066006292,
                "emo_anx": 0.1994950796022464,
                "emo_anger": 0.17735520943595948,
                "emo_sad": 0.0,
                "i": 0.9263052208835342,
                "we": 0.584351914036266,
                "you": 0.028096710711273537,
                "shehe": 0.2667146714671467,
                "they": 0.22576625019769092,
                "conflict": 0.0,
                "want": 0.18234716900046555,
                "comment_count": 0.15060240963855423
            },
            "away_vals": {
                "tone_pos": 0.32224388630093853,
                "tone_neg": 0.895949908503649,
                "emotion": 0.6484473752629467,
                "emo_pos": 0.3109170855315577,
                "emo_neg": 0.7945337749673791,
                "emo_anx": 0.9366571063824913,
                "emo_anger": 0.30826486550061327,
                "emo_sad": 0.0,
                "i": 0.5955731137108821,
                "we": 0.5593575106335349,
                "you": 0.5049573610720643,
                "shehe": 0.23402340234023405,
                "they": 0.17244978649375292,
                "conflict": 0.19850221610881857,
                "want": 0.1203707019701003,
                "comment_count": 0.5421686746987951
            },
            "neut_vals": {
                "tone_pos": 0.3744806223887048,
                "tone_neg": 0.8703551822210464,
                "emotion": 0.6834771325249953,
                "emo_pos": 0.2677075652164621,
                "emo_neg": 0.932228763666947,
                "emo_anx": 0.0,
                "emo_anger": 0.2111088008468169,
                "emo_sad": 0.1895585911311177,
                "i": 0.639596429195041,
                "we": 0.029382135661517803,
                "you": 0.22501405678942923,
                "shehe": 0.2798379837983798,
                "they": 0.014138858136960301,
                "conflict": 0.17518340210912423,
                "want": 0.010833363177309027,
                "comment_count": 0.24096385542168675
            },
            "wp_delta": -0.030246764499999967
        },
        {
            "start_utc": 1694291759,
            "end_utc": 1694293087,
            "home_vals": {
                "tone_pos": 0.3783043322821452,
                "tone_neg": 0.8958088056970257,
                "emotion": 0.7751648112694703,
                "emo_pos": 0.37790768229676897,
                "emo_neg": 0.9399340317796534,
                "emo_anx": 0.0,
                "emo_anger": 0.26574760152561455,
                "emo_sad": 0.1192925326437442,
                "i": 0.3158915856663369,
                "we": 0.6234236251026043,
                "you": 0.05935088870146501,
                "shehe": 0.5770977097709771,
                "they": 0.09653645421477147,
                "conflict": 0.9896530643435731,
                "want": 0.10130398277803641,
                "comment_count": 0.2710843373493976
            },
            "away_vals": {
                "tone_pos": 0.5937832694428202,
                "tone_neg": 0.7467891978538889,
                "emotion": 0.8313113188266169,
                "emo_pos": 0.5177886699762356,
                "emo_neg": 0.8192177384924629,
                "emo_anx": 0.7005553316179375,
                "emo_anger": 0.32081231857630393,
                "emo_sad": 0.5967575038826947,
                "i": 0.6807023490380961,
                "we": 0.41137294407353275,
                "you": 0.29855242631210477,
                "shehe": 0.304265720689716,
                "they": 0.18630396963466703,
                "conflict": 1.0,
                "want": 0.23136665044558813,
                "comment_count": 0.6144578313253012
            },
            "neut_vals": {
                "tone_pos": 0.43105093333840755,
                "tone_neg": 0.5394936023271979,
                "emotion": 0.5469044322163494,
                "emo_pos": 0.33327344668243086,
                "emo_neg": 0.5580162672153722,
                "emo_anx": 0.7318740479275807,
                "emo_anger": 0.20369041539106794,
                "emo_sad": 0.36159425920671956,
                "i": 0.7843926979451854,
                "we": 0.2860600377611922,
                "you": 0.07921663899512518,
                "shehe": 0.4226686819625359,
                "they": 0.1344238912147625,
                "conflict": 0.40693640618376536,
                "want": 0.3819067124619657,
                "comment_count": 0.3313253012048193
            },
            "wp_delta": 0.01721611620000002
        },
        {
            "start_utc": 1694293157,
            "end_utc": 1694294246,
            "home_vals": {
                "tone_pos": 0.37860298708159246,
                "tone_neg": 1.0,
                "emotion": 0.6329497270084385,
                "emo_pos": 0.2060957754907934,
                "emo_neg": 0.9292374025272818,
                "emo_anx": 0.6927778350249885,
                "emo_anger": 0.9262059579615909,
                "emo_sad": 0.5222180985218531,
                "i": 0.5833842616844189,
                "we": 0.0,
                "you": 0.21544372598631797,
                "shehe": 1.0,
                "they": 1.0,
                "conflict": 0.22165864282439243,
                "want": 0.0,
                "comment_count": 0.14457831325301204
            },
            "away_vals": {
                "tone_pos": 0.3529590023590475,
                "tone_neg": 0.8073825204398842,
                "emotion": 0.7049013453498822,
                "emo_pos": 0.3499991385095606,
                "emo_neg": 0.8314663198238832,
                "emo_anx": 0.6209411581624767,
                "emo_anger": 0.2565293469572919,
                "emo_sad": 0.277031385296193,
                "i": 0.2779284841228267,
                "we": 0.8203971985033098,
                "you": 0.14588509004951428,
                "shehe": 0.12505740369955365,
                "they": 0.06992934766821483,
                "conflict": 0.35791483030626275,
                "want": 0.1295581800388386,
                "comment_count": 0.5903614457831325
            },
            "neut_vals": {
                "tone_pos": 0.6984251388688787,
                "tone_neg": 0.4654276076460083,
                "emotion": 0.7571790399205848,
                "emo_pos": 0.6264898350307606,
                "emo_neg": 0.5120036549024494,
                "emo_anx": 0.0,
                "emo_anger": 0.2551035838499925,
                "emo_sad": 0.07668805669954985,
                "i": 0.14601158256213262,
                "we": 0.2320796955451086,
                "you": 0.054484115827944886,
                "shehe": 0.7269126912691268,
                "they": 0.20357425272813537,
                "conflict": 0.10392786183707778,
                "want": 0.3209564397330754,
                "comment_count": 0.18072289156626506
            },
            "wp_delta": 0.17934510110000002
        },
        {
            "start_utc": 1694294332,
            "end_utc": 1694295138,
            "home_vals": {
                "tone_pos": 0.28601889394282415,
                "tone_neg": 0.7356495611009798,
                "emotion": 0.6093040386543901,
                "emo_pos": 0.241630140562525,
                "emo_neg": 0.8263003457620781,
                "emo_anx": 0.0,
                "emo_anger": 1.0,
                "emo_sad": 0.0,
                "i": 1.0,
                "we": 1.0,
                "you": 0.056468131250251,
                "shehe": 0.15821010672495822,
                "they": 0.2535505298117982,
                "conflict": 0.6928276675181763,
                "want": 0.0,
                "comment_count": 0.21084337349397592
            },
            "away_vals": {
                "tone_pos": 0.4602272235225391,
                "tone_neg": 0.641260209984397,
                "emotion": 0.46200815313100474,
                "emo_pos": 0.22790692214879837,
                "emo_neg": 0.5560267846884234,
                "emo_anx": 0.516929360977542,
                "emo_anger": 0.05392384101856007,
                "emo_sad": 0.396196975668118,
                "i": 0.4255940368745116,
                "we": 0.49115370641535205,
                "you": 0.4638417896827773,
                "shehe": 0.2458278614746721,
                "they": 0.26015872316264066,
                "conflict": 0.15883073638953402,
                "want": 0.0373662231558331,
                "comment_count": 0.3674698795180723
            },
            "neut_vals": {
                "tone_pos": 0.46895696629164413,
                "tone_neg": 0.6150478927779014,
                "emotion": 0.7211855633553149,
                "emo_pos": 0.4436154044694971,
                "emo_neg": 0.7023659640985124,
                "emo_anx": 0.3778315901557697,
                "emo_anger": 0.24502357615165724,
                "emo_sad": 0.11983932805693173,
                "i": 0.3621931732198888,
                "we": 0.4006654862934246,
                "you": 0.26497474037535873,
                "shehe": 0.20205656929329296,
                "they": 0.3114747027446695,
                "conflict": 0.0,
                "want": 0.07090928625147727,
                "comment_count": 0.19879518072289157
            },
            "wp_delta": -0.042895972800000015
        },
        {
            "start_utc": 1694295156,
            "end_utc": 1694297163,
            "home_vals": {
                "tone_pos": 0.45319623796560987,
                "tone_neg": 0.6426907933899834,
                "emotion": 0.6022405087383426,
                "emo_pos": 0.35071895270434333,
                "emo_neg": 0.6089627083002028,
                "emo_anx": 0.7192322606712567,
                "emo_anger": 0.34350866581242157,
                "emo_sad": 0.30232030608078475,
                "i": 0.44570348518406194,
                "we": 0.5262804425435651,
                "you": 1.0,
                "shehe": 0.3522036414167733,
                "they": 0.13734319984684154,
                "conflict": 0.18317285648784956,
                "want": 0.3788256050002167,
                "comment_count": 0.3433734939759036
            },
            "away_vals": {
                "tone_pos": 0.4923044432448134,
                "tone_neg": 0.5616693907052245,
                "emotion": 0.6158911075059659,
                "emo_pos": 0.3814162745689567,
                "emo_neg": 0.5975965913931399,
                "emo_anx": 0.2687475131087491,
                "emo_anger": 0.3709446890844796,
                "emo_sad": 0.18642100246595036,
                "i": 0.8524393540637143,
                "we": 0.6124794679052006,
                "you": 0.2474663907245513,
                "shehe": 0.5071952978430375,
                "they": 0.15123216255818783,
                "conflict": 0.4523679311468707,
                "want": 0.3476595922780762,
                "comment_count": 1.0
            },
            "neut_vals": {
                "tone_pos": 0.5965596688023372,
                "tone_neg": 0.4978421875162279,
                "emotion": 0.6670732620631097,
                "emo_pos": 0.5216875355988914,
                "emo_neg": 0.49883188487057284,
                "emo_anx": 0.18434746766963778,
                "emo_anger": 0.12474802323997439,
                "emo_sad": 0.22698223231522902,
                "i": 0.675057398115639,
                "we": 0.20082811138431145,
                "you": 0.3330541337416382,
                "shehe": 0.06171195631959891,
                "they": 0.1533637526908845,
                "conflict": 0.4243219995377054,
                "want": 1.0,
                "comment_count": 0.7289156626506024
            },
            "wp_delta": 0.03399220110000001
        },
        {
            "start_utc": 1694297199,
            "end_utc": 1694298790,
            "home_vals": {
                "tone_pos": 1.0,
                "tone_neg": 0.47223977137696116,
                "emotion": 1.0,
                "emo_pos": 1.0,
                "emo_neg": 0.40392228892562415,
                "emo_anx": 0.15359831290496234,
                "emo_anger": 0.1616069705960569,
                "emo_sad": 0.469837494096549,
                "i": 0.6246537875640494,
                "we": 0.32648618605405155,
                "you": 0.5907971653757038,
                "shehe": 0.3103137899996896,
                "they": 0.08491167985515387,
                "conflict": 0.2983446378598871,
                "want": 0.19246030030860725,
                "comment_count": 0.3493975903614458
            },
            "away_vals": {
                "tone_pos": 0.42789031359554314,
                "tone_neg": 0.6257821284476488,
                "emotion": 0.6520971708147207,
                "emo_pos": 0.34398469644021246,
                "emo_neg": 0.7090259477307416,
                "emo_anx": 0.08312294983426934,
                "emo_anger": 0.24956399012046976,
                "emo_sad": 0.2906627717651566,
                "i": 0.711601478377277,
                "we": 0.5410230579807477,
                "you": 0.4945412801049571,
                "shehe": 0.1749054905490549,
                "they": 0.05974379250355843,
                "conflict": 0.19889194559070758,
                "want": 0.5120569661808066,
                "comment_count": 0.9036144578313253
            },
            "neut_vals": {
                "tone_pos": 0.5719640807612387,
                "tone_neg": 0.405161557238747,
                "emotion": 0.5925754480340476,
                "emo_pos": 0.47573939508306234,
                "emo_neg": 0.3854377280176413,
                "emo_anx": 0.14606487476750044,
                "emo_anger": 0.15594537706388778,
                "emo_sad": 0.14877927041625394,
                "i": 0.5415461085661584,
                "we": 0.2610868967506682,
                "you": 0.4888262675167406,
                "shehe": 0.1731072436102671,
                "they": 0.1734925333845649,
                "conflict": 0.018675627521394345,
                "want": 0.5079029651772479,
                "comment_count": 0.8975903614457831
            },
            "wp_delta": 0.27640762930000007
        },
        {
            "start_utc": 1694298821,
            "end_utc": 1694299850,
            "home_vals": {
                "tone_pos": 0.6823123697925598,
                "tone_neg": 0.4866912966655011,
                "emotion": 0.829934461765988,
                "emo_pos": 0.6903507472902493,
                "emo_neg": 0.46543669705990964,
                "emo_anx": 0.22829124436626116,
                "emo_anger": 0.20874288018549322,
                "emo_sad": 0.027925622887791265,
                "i": 0.6530833478842908,
                "we": 0.4709536601746138,
                "you": 0.21194626290212448,
                "shehe": 0.3175174660323175,
                "they": 0.10754388739522378,
                "conflict": 0.13250802384227414,
                "want": 0.6252398176618352,
                "comment_count": 0.25301204819277107
            },
            "away_vals": {
                "tone_pos": 0.5264442093214535,
                "tone_neg": 0.8914197894158572,
                "emotion": 0.8553191962138434,
                "emo_pos": 0.43489653263663297,
                "emo_neg": 1.0,
                "emo_anx": 0.2661655092702742,
                "emo_anger": 0.2859018281882531,
                "emo_sad": 1.0,
                "i": 0.8630506517902128,
                "we": 0.581609082314895,
                "you": 0.5071438931755629,
                "shehe": 0.48398470420290446,
                "they": 0.03365329889565039,
                "conflict": 0.8045059094612709,
                "want": 0.45433883123995894,
                "comment_count": 0.9457831325301205
            },
            "neut_vals": {
                "tone_pos": 0.6133500022462752,
                "tone_neg": 0.5376187621215774,
                "emotion": 0.6554914191215325,
                "emo_pos": 0.4675869762541786,
                "emo_neg": 0.5481708070695835,
                "emo_anx": 0.0,
                "emo_anger": 0.24625554260181562,
                "emo_sad": 0.1018020613524227,
                "i": 0.5099324366188458,
                "we": 0.08255432310058711,
                "you": 0.21594629399548362,
                "shehe": 0.31392816701024945,
                "they": 0.19122201078499895,
                "conflict": 0.4063872742601055,
                "want": 0.10197339919802496,
                "comment_count": 0.7469879518072289
            },
            "wp_delta": 0.05322268610000003
        },
        {
            "start_utc": 1694299891,
            "end_utc": 1694301009,
            "home_vals": {
                "tone_pos": 0.5768096668255144,
                "tone_neg": 0.3193434649218762,
                "emotion": 0.6111861633367701,
                "emo_pos": 0.5182432637948652,
                "emo_neg": 0.39353547116373017,
                "emo_anx": 0.26639306903617277,
                "emo_anger": 0.10022871616512931,
                "emo_sad": 0.14458532560246956,
                "i": 0.6211300049697116,
                "we": 0.7044480033062976,
                "you": 0.5436084859756491,
                "shehe": 0.09229384476909229,
                "they": 0.14379736979768606,
                "conflict": 0.2118779317885232,
                "want": 0.7878355036790733,
                "comment_count": 0.3132530120481928
            },
            "away_vals": {
                "tone_pos": 0.5899119791988253,
                "tone_neg": 0.49117383046875734,
                "emotion": 0.7027846152287763,
                "emo_pos": 0.569258226197728,
                "emo_neg": 0.49457481350949256,
                "emo_anx": 0.43538613652478353,
                "emo_anger": 0.09194011794949344,
                "emo_sad": 0.6773395633514396,
                "i": 0.6369390605901868,
                "we": 0.5981419297067384,
                "you": 0.43386347510609513,
                "shehe": 0.35190947666195194,
                "they": 0.15632724068593115,
                "conflict": 0.0,
                "want": 0.8134308122848034,
                "comment_count": 0.6325301204819277
            },
            "neut_vals": {
                "tone_pos": 0.4750203505897604,
                "tone_neg": 0.5828471536280493,
                "emotion": 0.555058269648976,
                "emo_pos": 0.32278647872306887,
                "emo_neg": 0.5760291705700376,
                "emo_anx": 1.0,
                "emo_anger": 0.08008893076872127,
                "emo_sad": 0.12489304323942246,
                "i": 0.690828351133604,
                "we": 0.2038780256314905,
                "you": 0.3761840812087442,
                "shehe": 0.1367541712848971,
                "they": 0.16674269327641575,
                "conflict": 0.19174046327979047,
                "want": 0.3800451240912509,
                "comment_count": 0.7289156626506024
            },
            "wp_delta": 0.11824834350000002
        },
        {
            "start_utc": 1694301041,
            "end_utc": 1694302285,
            "home_vals": {
                "tone_pos": 0.5601173985575533,
                "tone_neg": 0.3754737009885509,
                "emotion": 0.5323700224228541,
                "emo_pos": 0.4860842407076585,
                "emo_neg": 0.28804294374204337,
                "emo_anx": 0.0,
                "emo_anger": 0.2903341158621989,
                "emo_sad": 0.0,
                "i": 0.3220258081506353,
                "we": 0.4005603937068558,
                "you": 0.4737806311268013,
                "shehe": 0.6107036933201517,
                "they": 0.14557314825137474,
                "conflict": 0.3739486323764854,
                "want": 0.4950669375912564,
                "comment_count": 0.3674698795180723
            },
            "away_vals": {
                "tone_pos": 0.4518529190478477,
                "tone_neg": 0.8981345691992949,
                "emotion": 0.7444373537545209,
                "emo_pos": 0.3518750066792773,
                "emo_neg": 0.8920062972594318,
                "emo_anx": 0.0,
                "emo_anger": 0.142915556436208,
                "emo_sad": 0.5750740064313212,
                "i": 0.8510829926402259,
                "we": 0.622658113522151,
                "you": 0.4325758824270742,
                "shehe": 0.04866693565908315,
                "they": 0.043933750347663426,
                "conflict": 0.0,
                "want": 0.9394393695964394,
                "comment_count": 0.5240963855421686
            },
            "neut_vals": {
                "tone_pos": 0.6232861378438332,
                "tone_neg": 0.47993479913935544,
                "emotion": 0.6896548927901963,
                "emo_pos": 0.5662231052854189,
                "emo_neg": 0.452289996941472,
                "emo_anx": 0.15886804053056408,
                "emo_anger": 0.2812629080203017,
                "emo_sad": 0.08113856768843018,
                "i": 0.6662556265329777,
                "we": 0.05810169430409131,
                "you": 0.33203834767628987,
                "shehe": 0.47853375941621007,
                "they": 0.11243070201788082,
                "conflict": 0.08108465730577377,
                "want": 0.3670256195909797,
                "comment_count": 0.8975903614457831
            },
            "wp_delta": 0.010374708100000074
        }
    ]
}